madrigalWeb/__init__.py
madrigalWeb/exampleMadrigalWebServices.py
madrigalWeb/globalCitation.py
madrigalWeb/globalDownload.py
madrigalWeb/globalIsprint.py
madrigalWeb/madrigalWeb.py
madrigalWeb/tests/__init__.py
madrigalWeb/tests/testMadrigalWeb.py
madrigalweb-3.3.6.data/scripts/exampleMadrigalWebServices.py
madrigalweb-3.3.6.data/scripts/globalCitation.py
madrigalweb-3.3.6.data/scripts/globalDownload.py
madrigalweb-3.3.6.data/scripts/globalIsprint.py
madrigalweb-3.3.6.dist-info/METADATA
madrigalweb-3.3.6.dist-info/WHEEL
madrigalweb-3.3.6.dist-info/top_level.txt
madrigalweb-3.3.6.dist-info/RECORD
