Metadata-Version: 2.4
Name: madrigalWeb
Version: 3.3.6
Summary: Python Madrigal Remote API
Home-page: https://cedar.openmadrigal.org
Author-email: Bill Rideout <brideout@mit.edu>, Katherine Cariglia <cariglia@mit.edu>
Project-URL: Homepage, https://github.com/MITHaystack/madrigalWeb
Classifier: Programming Language :: Python :: 3
Classifier: License :: OSI Approved :: MIT License
Classifier: Operating System :: OS Independent
Requires-Python: >=3.3
Requires-Dist: packaging
Dynamic: home-page
